setup.cfg
setup.py
EVEPrest.egg-info/PKG-INFO
EVEPrest.egg-info/SOURCES.txt
EVEPrest.egg-info/dependency_links.txt
EVEPrest.egg-info/requires.txt
EVEPrest.egg-info/top_level.txt
prest/__init__.py
prest/cache.py
prest/errors.py
prest/prest.py