Metadata-Version: 1.1
Name: EVEPrest
Version: 1.3.0
Summary: EVE CREST access tool
Home-page: https://github.com/Celeo/Prest
Author: Matt Boulanger
Author-email: celeodor@gmail.com
License: MIT
Keywords: eve online,crest,api
Platform: any
Classifier: Development Status :: 3 - Alpha
Classifier: Environment :: Console
Classifier: Environment :: Web Environment
Classifier: Operating System :: OS Independent
Classifier: Programming Language :: Python :: 3
Classifier: Topic :: Software Development :: Libraries
